powspechi/__init__.py
powspechi/maps_manip.py
powspechi/monte_carlos.py
powspechi/powspec_analysis.py
powspechi/powspec_calc.py
powspechi/pserrors.py
powspechi/supmaps_iso/supmap_iso0.8_ns128.fits
powspechi/supmaps_iso/supmap_iso0.8_ns16.fits
powspechi/supmaps_iso/supmap_iso0.8_ns32.fits
powspechi/supmaps_iso/supmap_iso0.8_ns64.fits
powspechi/supmaps_iso/supmap_iso0.8_ns8.fits
powspechi/supmaps_iso/supmap_iso0.9_ns128.fits
powspechi/supmaps_iso/supmap_iso0.9_ns16.fits
powspechi/supmaps_iso/supmap_iso0.9_ns32.fits
powspechi/supmaps_iso/supmap_iso0.9_ns64.fits
powspechi/supmaps_iso/supmap_iso0.9_ns8.fits
powspechi-1.0.dist-info/LICENSE
powspechi-1.0.dist-info/METADATA
powspechi-1.0.dist-info/WHEEL
powspechi-1.0.dist-info/top_level.txt
powspechi-1.0.dist-info/RECORD
