Metadata-Version: 2.1
Name: powspechi
Version: 1.0
Summary: A package of angular power spectral analysis for heavy-ions
Home-page: https://github.com/m33ra/powspechi/
Author: Meera Vieira Machado
Author-email: machado.meera@protonmail.com
License: UNKNOWN
Platform: UNKNOWN
Classifier: Programming Language :: Python :: 3.6
Classifier: License :: OSI Approved :: MIT License
Requires-Dist: healpy (>=1.12.10)
